LICENSE.txt
MANIFEST.in
README.md
requirements.txt
setup.cfg
setup.py
charcad/__init__.py
charcad/version.py
charcad.egg-info/PKG-INFO
charcad.egg-info/SOURCES.txt
charcad.egg-info/dependency_links.txt
charcad.egg-info/requires.txt
charcad.egg-info/top_level.txt
charcad/draw/__init__.py
charcad/draw/block.py
charcad/draw/canvas.py
charcad/draw/coordinates.py
charcad/draw/graph.py
charcad/draw/lines.py
charcad/draw/point.py
charcad/draw/text.py
charcad/draw/utils.py
charcad/draw/vector.py