Metadata-Version: 1.2
Name: charcad
Version: 0.0.9
Summary: Character-based drawing tool
Home-page: https://github.com/vczoni/charcad
Author: Victor Zoni
Author-email: vczoni@gmail.com
License: MIT
Download-URL: https://github.com/vczoni/charcad/archive/v0.0.9.tar.gz
Keywords: CHARACTER,DRAWING,BASIC
Platform: UNKNOWN
Classifier: Development Status :: 3 - Alpha
Classifier: Intended Audience :: Developers
Classifier: Topic :: Software Development :: Build Tools
Classifier: License :: OSI Approved :: MIT License
Classifier: Programming Language :: Python :: 3
Requires-Python: >=3
